yamx/__init__.py
yamx/constants.py
yamx/containers/__init__.py
yamx/containers/data.py
yamx/containers/settings.py
yamx/extra/README.md
yamx/extra/__init__.py
yamx/extra/extra.py
yamx/jinja/__init__.py
yamx/jinja/condition.py
yamx/loader/__init__.py
yamx/loader/grouper.py
yamx/loader/preprocessor.py
yamx/loader/utils.py
yamx/loader/validator.py
yamx/py.typed
yamx/representer/__init__.py
yamx/representer/common.py
yamx/representer/conditional_map.py
yamx/representer/conditional_seq.py
yamx/representer/rendering.py
yamx/utils.py
yamx/yamx.py
yamx-1.0.0.dist-info/LICENSE
yamx-1.0.0.dist-info/METADATA
yamx-1.0.0.dist-info/WHEEL
yamx-1.0.0.dist-info/RECORD
