Metadata-Version: 2.1
Name: yamx
Version: 1.0.0
Summary: YAML parser that supports jinja conditional expressions
Home-page: https://github.com/maybelinot/yamx
License: Apache-2.0
Keywords: yaml,jinja,language
Author: Eduard Trott
Author-email: eduard.trott@workday.com
Requires-Python: >=3.9
Classifier: License :: OSI Approved :: Apache Software License
Classifier: Programming Language :: Python :: 3
Classifier: Programming Language :: Python :: 3.9
Classifier: Programming Language :: Python :: 3.10
Classifier: Programming Language :: Python :: 3.11
Classifier: Programming Language :: Python :: 3.12
Requires-Dist: immutables (>=0,<1)
Requires-Dist: jinja2 (>=3.1.2,<4.0.0)
Requires-Dist: ruamel.yaml (==0.18.3)
Requires-Dist: ruamel.yaml.string (==0.1.0)
Project-URL: Repository, https://github.com/maybelinot/yamx
